dolbyio_rest_apis/__init__.py
dolbyio_rest_apis/authentication.py
dolbyio_rest_apis/models.py
dolbyio_rest_apis/communications/__init__.py
dolbyio_rest_apis/communications/authentication.py
dolbyio_rest_apis/communications/conference.py
dolbyio_rest_apis/communications/models.py
dolbyio_rest_apis/communications/recording.py
dolbyio_rest_apis/communications/remix.py
dolbyio_rest_apis/communications/streaming.py
dolbyio_rest_apis/communications/internal/__init__.py
dolbyio_rest_apis/communications/internal/http_context.py
dolbyio_rest_apis/communications/monitor/__init__.py
dolbyio_rest_apis/communications/monitor/conferences.py
dolbyio_rest_apis/communications/monitor/models.py
dolbyio_rest_apis/communications/monitor/recordings.py
dolbyio_rest_apis/communications/monitor/webhooks.py
dolbyio_rest_apis/core/__init__.py
dolbyio_rest_apis/core/helpers.py
dolbyio_rest_apis/core/http_context.py
dolbyio_rest_apis/core/http_request_error.py
dolbyio_rest_apis/core/rate_limiter.py
dolbyio_rest_apis/core/urls.py
dolbyio_rest_apis/media/__init__.py
dolbyio_rest_apis/media/analyze.py
dolbyio_rest_apis/media/analyze_music.py
dolbyio_rest_apis/media/analyze_speech.py
dolbyio_rest_apis/media/diagnose.py
dolbyio_rest_apis/media/enhance.py
dolbyio_rest_apis/media/io.py
dolbyio_rest_apis/media/jobs.py
dolbyio_rest_apis/media/mastering.py
dolbyio_rest_apis/media/transcode.py
dolbyio_rest_apis/media/webhooks.py
dolbyio_rest_apis/media/internal/__init__.py
dolbyio_rest_apis/media/internal/http_context.py
dolbyio_rest_apis/media/models/__init__.py
dolbyio_rest_apis/media/models/analyze_music_response.py
dolbyio_rest_apis/media/models/analyze_response.py
dolbyio_rest_apis/media/models/analyze_speech_response.py
dolbyio_rest_apis/media/models/diagnose_response.py
dolbyio_rest_apis/media/models/enhance_response.py
dolbyio_rest_apis/media/models/job_response.py
dolbyio_rest_apis/media/models/jobs_response.py
dolbyio_rest_apis/media/models/mastering_response.py
dolbyio_rest_apis_cli-3.6.2.dist-info/LICENSE
dolbyio_rest_apis_cli-3.6.2.dist-info/METADATA
dolbyio_rest_apis_cli-3.6.2.dist-info/WHEEL
dolbyio_rest_apis_cli-3.6.2.dist-info/entry_points.txt
dolbyio_rest_apis_cli-3.6.2.dist-info/top_level.txt
dolbyio_rest_apis_cli-3.6.2.dist-info/RECORD
