Metadata-Version: 2.1
Name: dolbyio-rest-apis-cli
Version: 3.6.2
Summary: A command line wrapper for the Dolby.io REST APIs.
Home-page: https://github.com/dolbyio/dolbyio-rest-apis-client-python
Author: Dolby.io
Author-email: fabien.lavocat@dolby.com
License: MIT
Project-URL: Documentation, https://docs.dolby.io/communications-apis/reference
Project-URL: Source, https://github.com/dolbyio/dolbyio-rest-apis-client-python
Project-URL: Bug Tracker, https://github.com/dolbyio/dolbyio-rest-apis-client-python/issues
Platform: UNKNOWN
Classifier: License :: OSI Approved :: MIT License
Classifier: Programming Language :: Python
Classifier: Programming Language :: Python :: 3
Classifier: Programming Language :: Python :: 3.7
Classifier: Programming Language :: Python :: 3.8
Classifier: Programming Language :: Python :: 3.9
Classifier: Programming Language :: Python :: 3.10
Classifier: Programming Language :: Python :: 3 :: Only
Classifier: Operating System :: OS Independent
Classifier: Intended Audience :: Developers
Requires-Python: >=3.7
License-File: LICENSE
Requires-Dist: dolbyio-rest-apis
